setup.cfg
setup.py
src/twitter/__init__.py
src/twitter.common.util.egg-info/PKG-INFO
src/twitter.common.util.egg-info/SOURCES.txt
src/twitter.common.util.egg-info/dependency_links.txt
src/twitter.common.util.egg-info/namespace_packages.txt
src/twitter.common.util.egg-info/requires.txt
src/twitter.common.util.egg-info/top_level.txt
src/twitter.common.util.egg-info/zip-safe
src/twitter/common/__init__.py
src/twitter/common/util/__init__.py
src/twitter/common/util/command_util.py